fedata/__init__.py
fedata/exceptions/fetchdataexceptions.py
fedata/exceptions/generateexceptions.py
fedata/hub/fetch_data.py
fedata/hub/generate_dataset.py
fedata/load/load_cifar.py
fedata/load/load_fmnist.py
fedata/load/load_mnist.py
fedata/split/shard_splits.py
fedata/transform/shard_transformation.py
fedata/utils/custom_transformation.py
fedata/utils/load_from_json.py
fedata/utils/save_blueprint.py
fedata/utils/save_dataset.py
fedata/utils/showcase.py
fedata-0.3.7.dist-info/METADATA
fedata-0.3.7.dist-info/WHEEL
fedata-0.3.7.dist-info/RECORD
