Metadata-Version: 2.1
Name: fedata
Version: 0.3.7
Summary: 
Author: Scolpe
Author-email: maciejzuziak101@gmail.com
Requires-Python: >=3.10.9,<4.0.0
Classifier: Programming Language :: Python :: 3
Classifier: Programming Language :: Python :: 3.11
Requires-Dist: datasets (>=2.8.0)
Requires-Dist: matplotlib (>=3.7.1)
Requires-Dist: numpy (>=1.24.1)
Requires-Dist: scikit-learn (>=1.2.0)
Requires-Dist: torchaudio (>=2.0.2)
Requires-Dist: torchvision (>=0.15.1)
